MANIFEST.in
README.md
requirements.txt
setup.py
giovanni/VERSION
giovanni/__init__.py
giovanni/__main__.py
giovanni/odds.py
giovanni/utils.py
giovanni.egg-info/PKG-INFO
giovanni.egg-info/SOURCES.txt
giovanni.egg-info/dependency_links.txt
giovanni.egg-info/not-zip-safe
giovanni.egg-info/requires.txt
giovanni.egg-info/top_level.txt
giovanni/__pycache__/__init__.cpython-36.pyc
giovanni/__pycache__/__init__.cpython-37.pyc
giovanni/__pycache__/__init__.cpython-38.pyc
giovanni/__pycache__/__main__.cpython-36.pyc
giovanni/__pycache__/__main__.cpython-37.pyc
giovanni/__pycache__/odds.cpython-36.pyc
giovanni/__pycache__/odds.cpython-37.pyc
giovanni/__pycache__/odds.cpython-38.pyc
giovanni/__pycache__/utils.cpython-36.pyc
giovanni/__pycache__/utils.cpython-37.pyc
giovanni/__pycache__/utils.cpython-38.pyc
giovanni/cli/__init__.py
giovanni/cli/common.py
giovanni/cli/main.py
giovanni/cli/odds.py
giovanni/cli/parsers.py
giovanni/cli/simulate.py
giovanni/cli/simulate_test.py
giovanni/cli/__pycache__/__init__.cpython-36.pyc
giovanni/cli/__pycache__/__init__.cpython-37.pyc
giovanni/cli/__pycache__/__init__.cpython-38.pyc
giovanni/cli/__pycache__/common.cpython-36.pyc
giovanni/cli/__pycache__/common.cpython-37.pyc
giovanni/cli/__pycache__/common.cpython-38.pyc
giovanni/cli/__pycache__/main.cpython-36.pyc
giovanni/cli/__pycache__/main.cpython-37.pyc
giovanni/cli/__pycache__/odds.cpython-36.pyc
giovanni/cli/__pycache__/odds.cpython-37.pyc
giovanni/cli/__pycache__/parsers.cpython-36.pyc
giovanni/cli/__pycache__/parsers.cpython-37.pyc
giovanni/cli/__pycache__/simulate.cpython-36.pyc
giovanni/cli/__pycache__/simulate.cpython-37.pyc
giovanni/cli/__pycache__/simulate.cpython-38.pyc
giovanni/cli/__pycache__/simulate_test.cpython-36-pytest-5.2.2.pyc
giovanni/cli/__pycache__/simulate_test.cpython-37-PYTEST.pyc
giovanni/cli/__pycache__/simulate_test.cpython-38-pytest-6.2.1.pyc