Metadata-Version: 1.2
Name: giovanni
Version: 0.0.1
Summary: Simulate the odds/time required to SR for a shiny
Home-page: UNKNOWN
Author: Taylor Smith
Author-email: taylor.smith@alkaline-ml.com
License: UNKNOWN
Project-URL: Source Code, https://github.com/tgsmith61591/giovanni
Platform: UNKNOWN
Classifier: Intended Audience :: Developers
Classifier: Programming Language :: Python
Classifier: Topic :: Software Development
Classifier: Programming Language :: Python :: 3.7
Requires-Python: >=3.7
